vector_embed_cache/__init__.py
vector_embed_cache/cache.py
vector_embed_cache/cli.py
vector_embed_cache/normalize.py
vector_embed_cache/providers.py
vector_embed_cache/py.typed
vector_embed_cache/storage.py
vector_embed_cache/utils.py
vector_embed_cache-0.1.0.dist-info/METADATA
vector_embed_cache-0.1.0.dist-info/WHEEL
vector_embed_cache-0.1.0.dist-info/entry_points.txt
vector_embed_cache-0.1.0.dist-info/licenses/LICENSE
vector_embed_cache-0.1.0.dist-info/RECORD
