Metadata-Version: 2.4
Name: vector-embed-cache
Version: 0.1.0
Summary: Cache embedding vectors locally with smart fallback to remote compute
Author-email: Gabe <gabe@signalnine.net>
License: MIT
License-File: LICENSE
Keywords: cache,embeddings,machine-learning,nlp,vectors
Classifier: Development Status :: 4 - Beta
Classifier: Intended Audience :: Developers
Classifier: License :: OSI Approved :: MIT License
Classifier: Programming Language :: Python :: 3
Classifier: Programming Language :: Python :: 3.8
Classifier: Programming Language :: Python :: 3.9
Classifier: Programming Language :: Python :: 3.10
Classifier: Programming Language :: Python :: 3.11
Classifier: Programming Language :: Python :: 3.12
Classifier: Topic :: Scientific/Engineering :: Artificial Intelligence
Requires-Python: >=3.8
Requires-Dist: httpx>=0.24
Requires-Dist: msgpack>=1.0
Requires-Dist: numpy>=1.20
Provides-Extra: dev
Requires-Dist: pytest-asyncio>=0.21; extra == 'dev'
Requires-Dist: pytest-mock>=3.10; extra == 'dev'
Requires-Dist: pytest>=7.0; extra == 'dev'
Provides-Extra: local
Requires-Dist: einops>=0.8; extra == 'local'
Requires-Dist: sentence-transformers>=2.3; extra == 'local'
Requires-Dist: torch>=2.0; extra == 'local'
Provides-Extra: openai
Requires-Dist: openai>=1.0.0; extra == 'openai'
